respona_mcp_server/__init__.py
respona_mcp_server/__main__.py
respona_mcp_server/client.py
respona_mcp_server/config.py
respona_mcp_server/server.py
mcp_respona_dashboard-1.0.2.dist-info/METADATA
mcp_respona_dashboard-1.0.2.dist-info/WHEEL
mcp_respona_dashboard-1.0.2.dist-info/entry_points.txt
mcp_respona_dashboard-1.0.2.dist-info/licenses/LICENSE
mcp_respona_dashboard-1.0.2.dist-info/RECORD
