Metadata-Version: 2.4
Name: mcp-respona-dashboard
Version: 1.0.2
Summary: MCP server for Respona Dashboard API integration - enables natural language interactions with ticket management and analytics systems
Project-URL: Homepage, https://github.com/raihan0824/mcp-respona-dashboard
Project-URL: Repository, https://github.com/raihan0824/mcp-respona-dashboard
Project-URL: Issues, https://github.com/raihan0824/mcp-respona-dashboard/issues
Project-URL: Changelog, https://github.com/raihan0824/mcp-respona-dashboard/releases
Author-email: raihan0824 <raihan0824@users.noreply.github.com>
Maintainer-email: raihan0824 <raihan0824@users.noreply.github.com>
License: MIT
License-File: LICENSE
Keywords: analytics,api,dashboard,mcp,model-context-protocol,respona,tickets
Classifier: Development Status :: 4 - Beta
Classifier: Intended Audience :: Developers
Classifier: Intended Audience :: System Administrators
Classifier: License :: OSI Approved :: MIT License
Classifier: Operating System :: OS Independent
Classifier: Programming Language :: Python :: 3
Classifier: Programming Language :: Python :: 3.10
Classifier: Programming Language :: Python :: 3.11
Classifier: Programming Language :: Python :: 3.12
Classifier: Topic :: Communications
Classifier: Topic :: Software Development :: Libraries :: Python Modules
Classifier: Topic :: System :: Systems Administration
Requires-Python: >=3.10
Requires-Dist: httpx>=0.25.0
Requires-Dist: mcp>=1.0.0
Requires-Dist: pydantic-settings>=2.0.0
Requires-Dist: pydantic>=2.0.0
Requires-Dist: python-dotenv>=1.0.0
Provides-Extra: dev
Requires-Dist: build>=1.0.0; extra == 'dev'
Requires-Dist: mypy>=1.0.0; extra == 'dev'
Requires-Dist: pytest-asyncio>=0.21.0; extra == 'dev'
Requires-Dist: pytest>=7.0.0; extra == 'dev'
Requires-Dist: ruff>=0.7.4; extra == 'dev'
Requires-Dist: twine>=4.0.0; extra == 'dev'
